{"sections":{"product-grid":{"type":"main-usf-collection","settings":{"usf_show_description":false,"usf_show_grid_border":true,"usf_columns_desktop":4,"usf_columns_mobile":"2","usf_text_alignment":"left","usf_heading_font":"assistant_n4","usf_image_style":"natural","usf_image_size":"cover","usf_sale_type":"text","usf_sale_label_position":"top-right","usf_sale_color":"#ff4e4e","usf_sale_text_color":"#ffffff","usf_soldout_color":"#000000","usf_soldout_text_color":"#ffffff","usf_soldout_label_position":"top-right"}}},"order":["product-grid"]}